CHANGES.rst
LICENSE.rst
MANIFEST.in
README.rst
setup.py
src/zperfmetrics/__init__.py
src/zperfmetrics/component.xml
src/zperfmetrics/config.py
src/zperfmetrics/configure.zcml
src/zperfmetrics/patches.py
src/zperfmetrics/subscribers.py
src/zperfmetrics.egg-info/PKG-INFO
src/zperfmetrics.egg-info/SOURCES.txt
src/zperfmetrics.egg-info/dependency_links.txt
src/zperfmetrics.egg-info/entry_points.txt
src/zperfmetrics.egg-info/requires.txt
src/zperfmetrics.egg-info/top_level.txt
src/zperfmetrics.egg-info/zip-safe