Metadata-Version: 1.1
Name: zperfmetrics
Version: 1.0a5
Summary: Perfmetrics configuration for Zope/Plone.
Home-page: http://github.com/collective/zperfmetrics
Author: BlueDynamics Alliance
Author-email: dev@bluedynamics.com
License: Simplified BSD
Keywords: plone zope perfmetrics statsd graphite monitor performance
Platform: UNKNOWN
Classifier: License :: OSI Approved :: BSD License
Classifier: Operating System :: OS Independent
Classifier: Programming Language :: Python :: 2.7
Classifier: Programming Language :: Python
Classifier: Topic :: Software Development
